talus/__init__.py
talus/_version.py
talus/base.py
talus/consumer.py
talus/producer.py
talus/models/__init__.py
talus/models/binding.py
talus/models/connection_parameters.py
talus/models/exchange.py
talus/models/message.py
talus/models/processor.py
talus/models/queue.py
talus/models/retryer.py
talus/tests/__init__.py
talus/tests/conftest.py
talus/tests/test_base.py
talus/tests/test_consumer.py
talus/tests/test_producer.py
talus/tests/models/__init__.py
talus/tests/models/test_binding.py
talus/tests/models/test_connection_parameters.py
talus/tests/models/test_message.py
talus/tests/models/test_processor.py
talus/tests/models/test_queue.py
talus/tests/models/test_retryer.py
talus-1.3.4.dist-info/licenses/LICENSE
talus-1.3.4.dist-info/METADATA
talus-1.3.4.dist-info/WHEEL
talus-1.3.4.dist-info/top_level.txt
talus-1.3.4.dist-info/RECORD
