Metadata-Version: 2.4
Name: talus
Version: 1.3.4
Summary: A wrapper for connecting to RabbitMQ which constrains clients to a single purpose channel (producer or consumer) with healing for intermittent connectivity.
Author-email: NSO / AURA <dkistdc@nso.edu>
License: MIT
Project-URL: repository, https://bitbucket.org/dkistdc/interservice-bus-adapter
Classifier: License :: OSI Approved :: MIT License
Classifier: Programming Language :: Python :: 3
Classifier: Programming Language :: Python :: 3.11
Requires-Python: >=3.11
License-File: LICENSE
Requires-Dist: pika~=1.3
Requires-Dist: tenacity~=8.2
Requires-Dist: pydantic~=2.0
Provides-Extra: test
Requires-Dist: tox>=4; extra == "test"
Requires-Dist: pytest; extra == "test"
Requires-Dist: pytest-cov; extra == "test"
Dynamic: license-file
